setup.py
autobi/__init__.py
autobi.egg-info/PKG-INFO
autobi.egg-info/SOURCES.txt
autobi.egg-info/dependency_links.txt
autobi.egg-info/top_level.txt