Metadata-Version: 1.1
Name: autobi
Version: 0.0.0
Summary: Namespace package for AutoBI releases
Home-page: UNKNOWN
Author: AutoBI
Author-email: chriscz93@gmail.com
License: UNKNOWN
Platform: UNKNOWN
Classifier: Programming Language :: Python :: 3.5
